{
  "SKU-PAN-001": {
    "type": "pan",
    "category": "cookware",
    "price": 149.95,
    "name": "GreenPan Reserve Ceramic Nonstick Fry Pan Set, 10\" & 12\"",
    "image": "/images/pan_1.jpg"
  },
  "SKU-PAN-002": {
    "type": "pan",
    "category": "cookware",
    "price": 99.95,
    "name": "All-Clad HA1 Hard Anodized Nonstick Fry Pan, 12\"",
    "image": "/images/pan_2.jpg"
  },
  "SKU-PAN-003": {
    "type": "pan",
    "category": "cookware",
    "price": 109.95,
    "name": "Le Creuset Toughened Nonstick PRO Fry Pan, 11\"",
    "image": "/images/pan_3.jpg"
  },
  "SKU-PAN-004": {
    "type": "pan",
    "category": "cookware",
    "price": 249.95,
    "name": "Staub Enameled Cast Iron Deep Skillet, 12\"",
    "image": "/images/pan_4.jpg"
  },
  "SKU-POT-001": {
    "type": "pot",
    "category": "cookware",
    "price": 299.95,
    "name": "Le Creuset Enameled Cast Iron Soup Pot, 4.5-Qt., White",
    "image": "/images/pot_1.jpg"
  },
  "SKU-POT-002": {
    "type": "pot",
    "category": "cookware",
    "price": 349.95,
    "name": "Staub Enameled Cast Iron Round Dutch Oven, 7-Qt., Cherry",
    "image": "/images/pot_2.jpg"
  },
  "SKU-POT-003": {
    "type": "pot",
    "category": "cookware",
    "price": 259.95,
    "name": "All-Clad Stainless-Steel Stockpot, 8-Qt.",
    "image": "/images/pot_3.jpg"
  },
  "SKU-POT-004": {
    "type": "pot",
    "category": "cookware",
    "price": 279.95,
    "name": "Le Creuset Cast Iron Braiser, 3.5-Qt., Artichaut",
    "image": "/images/pot_4.jpg"
  },
  "SKU-POT-005": {
    "type": "pot",
    "category": "cookware",
    "price": 189.95,
    "name": "Signature Stainless Steel Saucepan with Lid, 3-Qt.",
    "image": "/images/pot_5.jpg"
  },
  "SKU-KNF-001": {
    "type": "knife",
    "category": "cookware",
    "price": 449.95,
    "name": "W\u00fcsthof Performer 7-Piece Knife Block Set",
    "image": "/images/knife_1.jpg"
  },
  "SKU-KNF-002": {
    "type": "knife",
    "category": "cookware",
    "price": 149.95,
    "name": "Shun Classic Chef's Knife, 8\"",
    "image": "/images/knife_2.jpg"
  },
  "SKU-KNF-003": {
    "type": "knife",
    "category": "cookware",
    "price": 129.95,
    "name": "W\u00fcsthof Classic Santoku Knife, 7\"",
    "image": "/images/knife_3.jpg"
  },
  "SKU-KNF-004": {
    "type": "knife",
    "category": "cookware",
    "price": 99.95,
    "name": "Zwilling Pro Bread Knife, 9\"",
    "image": "/images/knife_4.jpg"
  },
  "SKU-KNF-005": {
    "type": "knife",
    "category": "cookware",
    "price": 59.95,
    "name": "Miyabi Kaizen II Paring Knife, 3.5\"",
    "image": "/images/knife_5.jpg"
  },
  "SKU-CB-001": {
    "type": "cutting_board",
    "category": "cookware",
    "price": 129.95,
    "name": "Williams Sonoma Acacia Cutting Board Set, 3-Piece",
    "image": "/images/cutting_board_1.jpg"
  },
  "SKU-CB-002": {
    "type": "cutting_board",
    "category": "cookware",
    "price": 149.95,
    "name": "Williams Sonoma End-Grain Cutting Board, Walnut, 18\" \u00d7 14\"",
    "image": "/images/cutting_board_2.jpg"
  },
  "SKU-CB-003": {
    "type": "cutting_board",
    "category": "cookware",
    "price": 189.95,
    "name": "John Boos Maple Carving Board with Groove, 24\" \u00d7 18\"",
    "image": "/images/cutting_board_3.jpg"
  },
  "SKU-SPT-001": {
    "type": "spatula",
    "category": "cookware",
    "price": 39.95,
    "name": "Williams Sonoma Silicone Spatula Set, 4-Piece, Charcoal",
    "image": "/images/spatula_1.jpg"
  },
  "SKU-SPT-002": {
    "type": "spatula",
    "category": "cookware",
    "price": 19.95,
    "name": "Sur La Table Silicone Slotted Turner",
    "image": "/images/spatula_2.jpg"
  },
  "SKU-SPT-003": {
    "type": "spatula",
    "category": "cookware",
    "price": 12.95,
    "name": "OXO Good Grips Silicone Flexible Turner",
    "image": "/images/spatula_3.jpg"
  },
  "SKU-SOFA-001": {
    "type": "sofa",
    "category": "furniture",
    "price": 2999.0,
    "name": "Harlow Curved Velvet Sofa, Camel",
    "image": "/images/sofa_1.jpg"
  },
  "SKU-SOFA-002": {
    "type": "sofa",
    "category": "furniture",
    "price": 2499.0,
    "name": "Milo Upholstered Sofa, Linen, Oatmeal",
    "image": "/images/sofa_2.jpg"
  },
  "SKU-SOFA-003": {
    "type": "sofa",
    "category": "furniture",
    "price": 3599.0,
    "name": "Andover Tufted Sofa, Performance Linen, Navy",
    "image": "/images/sofa_3.jpg"
  },
  "SKU-SOFA-004": {
    "type": "sofa",
    "category": "furniture",
    "price": 4799.0,
    "name": "Belgrave Leather Sofa, Cognac",
    "image": "/images/sofa_4.jpg"
  },
  "SKU-SOFA-005": {
    "type": "sofa",
    "category": "furniture",
    "price": 3299.0,
    "name": "Huxley Boucle Sofa, Ivory",
    "image": "/images/sofa_5.jpg"
  },
  "SKU-CHR-001": {
    "type": "chair",
    "category": "furniture",
    "price": 1349.0,
    "name": "Bobbin Armchair, Striped Linen, Sage",
    "image": "/images/chair_1.jpg"
  },
  "SKU-CHR-002": {
    "type": "chair",
    "category": "furniture",
    "price": 1649.0,
    "name": "Essex Wingback Chair, Velvet, Emerald",
    "image": "/images/chair_2.jpg"
  },
  "SKU-CHR-003": {
    "type": "chair",
    "category": "furniture",
    "price": 1999.0,
    "name": "Lancaster Leather Club Chair, Chestnut",
    "image": "/images/chair_3.jpg"
  },
  "SKU-CHR-004": {
    "type": "chair",
    "category": "furniture",
    "price": 749.0,
    "name": "Waverly Upholstered Dining Chair, Set of 2",
    "image": "/images/chair_4.jpg"
  },
  "SKU-CHR-005": {
    "type": "chair",
    "category": "furniture",
    "price": 999.0,
    "name": "Harrington Rattan Accent Chair, Natural",
    "image": "/images/chair_5.jpg"
  },
  "SKU-CT-001": {
    "type": "coffee_table",
    "category": "furniture",
    "price": 1599.0,
    "name": "Pedestal Round Coffee Table, White Oak, Set of 2",
    "image": "/images/coffee_table_1.jpg"
  },
  "SKU-CT-002": {
    "type": "coffee_table",
    "category": "furniture",
    "price": 1899.0,
    "name": "Marble Top Coffee Table, Brass Base, 42\"",
    "image": "/images/coffee_table_2.jpg"
  },
  "SKU-CT-003": {
    "type": "coffee_table",
    "category": "furniture",
    "price": 1249.0,
    "name": "Driftwood Round Coffee Table, Weathered, 36\"",
    "image": "/images/coffee_table_3.jpg"
  },
  "SKU-CT-004": {
    "type": "coffee_table",
    "category": "furniture",
    "price": 2399.0,
    "name": "Walnut Live-Edge Coffee Table, 48\"",
    "image": "/images/coffee_table_4.jpg"
  },
  "SKU-CT-005": {
    "type": "coffee_table",
    "category": "furniture",
    "price": 1399.0,
    "name": "Stone Drum Coffee Table, Ivory, 32\"",
    "image": "/images/coffee_table_5.jpg"
  },
  "SKU-TBL-001": {
    "type": "table",
    "category": "dining",
    "price": 4299.0,
    "name": "Tulip Oval Dining Table, Carrara Marble, Brass Base, 72\"",
    "image": "/images/table_1.jpg"
  },
  "SKU-TBL-002": {
    "type": "table",
    "category": "dining",
    "price": 2899.0,
    "name": "Farmhouse Reclaimed Wood Dining Table, 84\"",
    "image": "/images/table_2.jpg"
  },
  "SKU-TBL-003": {
    "type": "table",
    "category": "dining",
    "price": 3399.0,
    "name": "Walnut Extending Dining Table, 60\"\u201384\"",
    "image": "/images/table_3.jpg"
  },
  "SKU-TBL-004": {
    "type": "table",
    "category": "dining",
    "price": 2399.0,
    "name": "Glass Top Trestle Dining Table, Iron Base, 72\"",
    "image": "/images/table_4.jpg"
  },
  "SKU-PLT-001": {
    "type": "plate",
    "category": "dining",
    "price": 74.95,
    "name": "Berry Meadow Porcelain Salad Plates, Set of 5",
    "image": "/images/plate_1.jpg"
  },
  "SKU-PLT-002": {
    "type": "plate",
    "category": "dining",
    "price": 64.95,
    "name": "Artisan Stoneware Dinner Plates, Set of 4, Fog",
    "image": "/images/plate_2.jpg"
  },
  "SKU-PLT-003": {
    "type": "plate",
    "category": "dining",
    "price": 19.95,
    "name": "Apilco Tradition Porcelain Dinner Plate, White, Each",
    "image": "/images/plate_3.jpg"
  },
  "SKU-PLT-004": {
    "type": "plate",
    "category": "dining",
    "price": 84.95,
    "name": "Rustic Hand-Painted Ceramic Plates, Set of 4",
    "image": "/images/plate_4.jpg"
  },
  "SKU-PLT-005": {
    "type": "plate",
    "category": "dining",
    "price": 129.95,
    "name": "Goldrim Bone China Charger Plates, Set of 4",
    "image": "/images/plate_5.jpg"
  },
  "SKU-GLS-001": {
    "type": "glass",
    "category": "dining",
    "price": 74.95,
    "name": "Dorset Martini Glasses, Set of 4",
    "image": "/images/glass_1.jpg"
  },
  "SKU-GLS-002": {
    "type": "glass",
    "category": "dining",
    "price": 99.95,
    "name": "Estate Wine Glasses, Set of 6, Bordeaux",
    "image": "/images/glass_2.jpg"
  },
  "SKU-GLS-003": {
    "type": "glass",
    "category": "dining",
    "price": 59.95,
    "name": "Handblown Double Old-Fashioned Glasses, Set of 4",
    "image": "/images/glass_3.jpg"
  }
}